Workbook

Sheet 说明
A1: 大厂裁员与 QQQ 模型 | Big Tech Layoff Model
A4: 用途 | B4: 本工作簿配合《大厂裁员与QQQ_深度研究_2026Q4.docx》使用，用于复算与情景调整。
A5: 基线 | B5: 八家公司（MSFT、GOOGL、AMZN、META、AAPL、NVDA、AVGO、TSLA）日历化 FY2026E 合并口径，美元十亿。
A6: 工作表 | B6: 假设：可调参数；推演：单情景五年公式模型；情景对比：不裁员/10%/20% 三情景结果；敏感性：EPS 增速矩阵；QQQ：指数情景与概率加权。
A7: 使用方法 | B7: 修改“假设”页蓝字单元格和“推演”页的增速/资本开支，表格会自动重算。情景对比与敏感性为模型输出值，不随假设联动。
A8: 口径提醒 | B8: 人力成本为全成本估算（含股权激励）；亚马逊仅计入企业岗位；折旧按 8 年混合年限简化。
A9: 重要提示 | B9: 所有情景均为假设推演，不构成投资建议。

Sheet 假设
A1: 核心假设
A2: 蓝字单元格可修改；修改后“推演”页自动重算。
A4: 参数 | B4: 取值 | C4: 单位 | D4: 说明
A5: 每年裁员比例 | B5: 0.1 | C5: % | D5: 作用于企业/专业岗位，每年复利
A6: 人均薪酬增速 | B6: 0.05 | C6: % | D6: 含股权激励，反映 AI 人才溢价
A7: AI 替代成本率 | B7: 0.2 | C7: % | D7: 被裁员工薪酬中用于推理/工具的比例
A8: 留存员工 token 预算 | B8: 0.08 | C8: % | D8: 占人力成本
A9: 其他费用收入弹性 | B9: 0.75 | C9: 指数 | D9: 其他费用 = 基期 × (收入/基期收入)^弹性
A10: 折旧年限 | B10: 8 | C10: 年 | D10: 服务器 5-6 年、建筑 15-20 年的混合
A11: 实际税率 | B11: 0.18 | C11: % | D11: —
A12: 股权激励 | B12: 0.025 | C12: % 收入 | D12: 加回 FCF
A13: 营运资金变动 | B13: 0.02 | C13: % 收入增量 | D13: —
A14: 回购比例 | B14: 0.6 | C14: % FCF | D14: 上限为净利润的 90%
A15: 回购估值倍数 | B15: 25 | C15: x EPS | D15: 用于把回购金额换算成股数
A16: 基期收入 | B16: 2936.8 | C16: 十亿美元 | D16: 2026E 八家合计
... A25: 收入拖累系数 | B25: 0.05 | C25: 百分点/10%裁员 | D25: 每裁 10%，收入增速下降 0.5 个百分点

Sheet 推演
A1: 单情景五年推演（公式联动）
A2: 修改 C5:G5 的收入增速和 C14:G14 的资本开支，整张表自动重算。
A4: 项目（十亿美元） | B4: 2026A | C4: 2027E | D4: 2028E | E4: 2029E | F4: 2030E | G4: 2031E
A5: 收入增速（假设） | C5: 0.12 | D5: 0.1 | E5: 0.08 | F5: 0.07 | G5: 0.06
A6: 收入 | B6: =假设!$B$16 -> 2936.8 | C6: =B6*(1+C5-假设!$B$25*假设!$B$5) -> 3274.532 | D6: =C6*(1+D5-假设!$B$25*假设!$B$5) -> 3585.6125 | E6: =D6*(1+E5-假设!$B$25*假设!$B$5) -> 3854.5335 | F6: =E6*(1+F5-假设!$B$25*假设!$B$5) -> 4105.0782 | G6: =F6*(1+G5-假设!$B$25*假设!$B$5) -> 4330.8575
A7: 员工数（千人） | B7: =假设!$B$21 -> 1189 | C7: =MAX(B7*(1-假设!$B$5),假设!$B$21*0.35) -> 1070.1 | D7: =MAX(C7*(1-假设!$B$5),假设!$B$21*0.35) -> 963.09 | E7: =MAX(D7*(1-假设!$B$5),假设!$B$21*0.35) -> 866.781 | F7: =MAX(E7*(1-假设!$B$5),假设!$B$21*0.35) -> 780.1029 | G7: =MAX(F7*(1-假设!$B$5),假设!$B$21*0.35) -> 702.09261
A8: 人均薪酬（百万美元） | B8: =假设!$B$17/假设!$B$21 -> 0.27603028 | C8: =B8*(1+假设!$B$6) -> 0.28983179 | D8: =C8*(1+假设!$B$6) -> 0.30432338 | E8: =D8*(1+假设!$B$6) -> 0.31953955 | F8: =E8*(1+假设!$B$6) -> 0.33551653 | G8: =F8*(1+假设!$B$6) -> 0.35229235
A9: 人力成本 | B9: =假设!$B$17 -> 328.2 | C9: =ROUND(C7*C8,1) -> 310.1 | D9: =ROUND(D7*D8,1) -> 293.1 | E9: =ROUND(E7*E8,1) -> 277 | F9: =ROUND(F7*F8,1) -> 261.7 | G9: =ROUND(G7*G8,1) -> 247.3
A10: 相对基准累计减员（千人） | B10: 0 | C10: =假设!$B$21-C7 -> 118.9 | D10: =假设!$B$21-D7 -> 225.91 | E10: =假设!$B$21-E7 -> 322.219 | F10: =假设!$B$21-F7 -> 408.8971 | G10: =假设!$B$21-G7 -> 486.90739
A11: AI 推理/工具成本 | B11: 0 | C11: =ROUND(C10*假设!$B$17/假设!$B$21*假设!$B$7+C9*假设!$B$8,1) -> 31.4 | D11: =ROUND(D10*假设!$B$17/假设!$B$21*假设!$B$7+D9*假设!$B$8,1) -> 35.9 | E11: =ROUND(E10*假设!$B$17/假设!$B$21*假设!$B$7+E9*假设!$B$8,1) -> 39.9 | F11: =ROUND(F10*假设!$B$17/假设!$B$21*假设!$B$7+F9*假设!$B$8,1) -> 43.5 | G11: =ROUND(G10*假设!$B$17/假设!$B$21*假设!$B$7+G9*假设!$B$8,1) -> 46.7
A12: 其他费用 | B12: =假设!$B$18 -> 1488.6 | C12: =ROUND(假设!$B$18*(C6/假设!$B$16)^假设!$B$9,1) -> 1615.2 | D12: =ROUND(假设!$B$18*(D6/假设!$B$16)^假设!$B$9,1) -> 1729 | E12: =ROUND(假设!$B$18*(E6/假设!$B$16)^假设!$B$9,1) -> 1825.4 | F12: =ROUND(假设!$B$18*(F6/假设!$B$16)^假设!$B$9,1) -> 1913.7 | G12: =ROUND(假设!$B$18*(G6/假设!$B$16)^假设!$B$9,1) -> 1992.1
A13: 折旧 | B13: =假设!$B$19 -> 190 | C13: =ROUND(AVERAGEIFS($B$28:$B$40,$A$28:$A$40,">="&2019,$A$28:$A$40,"<"&2027),1) -> 242.5 | D13: =ROUND(AVERAGEIFS($B$28:$B$40,$A$28:$A$40,">="&2020,$A$28:$A$40,"<"&2028),1) -> 345 | E13: =ROUND(AVERAGEIFS($B$28:$B$40,$A$28:$A$40,">="&2021,$A$28:$A$40,"<"&2029),1) -> 460.6 | F13: =ROUND(AVERAGEIFS($B$28:$B$40,$A$28:$A$40,">="&2022,$A$28:$A$40,"<"&2030),1) -> 581.9 | G13: =ROUND(AVERAGEIFS($B$28:$B$40,$A$28:$A$40,">="&2023,$A$28:$A$40,"<"&2031),1) -> 701.9
A14: 资本开支（假设） | B14: =假设!$B$20 -> 715 | C14: 900 | D14: 1020 | E14: 1100 | F14: 1120 | G14: 1100
A15: 经营利润 EBIT | B15: =B6-B9-B11-B12-B13 -> 930 | C15: =C6-C9-C11-C12-C13 -> 1075.332 | D15: =D6-D9-D11-D12-D13 -> 1182.6125 | E15: =E6-E9-E11-E12-E13 -> 1251.6335 | F15: =F6-F9-F11-F12-F13 -> 1304.2782 | G15: =G6-G9-G11-G12-G13 -> 1342.8575
A16: EBIT 利润率 | B16: =B15/B6 -> 0.31667121 | C16: =C15/C6 -> 0.32839258 | D16: =D15/D6 -> 0.32982162 | E16: =E15/E6 -> 0.32471724 | F16: =F15/F6 -> 0.3177231 | G16: =G15/G6 -> 0.31006734
A17: 净利润 | B17: =假设!$B$22 -> 763.4 | C17: =C15*(1-假设!$B$11) -> 881.77224 | D17: =D15*(1-假设!$B$11) -> 969.74228 | E17: =E15*(1-假设!$B$11) -> 1026.3395 | F17: =F15*(1-假设!$B$11) -> 1069.5081 | G17: =G15*(1-假设!$B$11) -> 1101.1431
A18: 股本（十亿股） | B18: =假设!$B$23 -> 78.2 | C18: =B18-MIN(B20*假设!$B$14,C17*0.9)/(假设!$B$15*B19) -> 77.418006 | D18: =C18-MIN(C20*假设!$B$14,D17*0.9)/(假设!$B$15*C19) -> 76.787164 | E18: =D18-MIN(D20*假设!$B$14,E17*0.9)/(假设!$B$15*D19) -> 76.068509 | F18: =E18-MIN(E20*假设!$B$14,F17*0.9)/(假设!$B$15*E19) -> 75.218381 | G18: =F18-MIN(F20*假设!$B$14,G17*0.9)/(假设!$B$15*F19) -> 74.15664
A19: EPS（美元） | B19: =假设!$B$24 -> 9.57 | C19: =C17/C18 -> 11.389756 | D19: =D17/D18 -> 12.628963 | E19: =E17/E18 -> 13.492304 | F19: =F17/F18 -> 14.218707 | G19: =G17/G18 -> 14.848881
A20: 自由现金流 | B20: =B17+B13+B6*假设!$B$12-B14 -> 311.82 | C20: =C17+C13+C6*假设!$B$12-C14-假设!$B$13*(C6-B6) -> 299.3809 | D20: =D17+D13+D6*假设!$B$12-D14-假设!$B$13*(D6-C6) -> 378.16099 | E20: =E17+E13+E6*假设!$B$12-E14-假设!$B$13*(E6-D6) -> 477.92437 | F20: =F17+F13+F6*假设!$B$12-F14-假设!$B$13*(F6-E6) -> 629.02415 | G20: =G17+G13+G6*假设!$B$12-G14-假设!$B$13*(G6-F6) -> 806.79896
A21: 资本开支/收入 | B21: =B14/B6 -> 0.24346227 | C21: =C14/C6 -> 0.27484844 | D21: =D14/D6 -> 0.28447022 | E21: =E14/E6 -> 0.28537825 | F21: =F14/F6 -> 0.27283281 | G21: =G14/G6 -> 0.25399127
A22: 折旧/收入 | B22: =B13/B6 -> 0.064696268 | C22: =C13/C6 -> 0.074056384 | D22: =D13/D6 -> 0.09621787 | E22: =E13/E6 -> 0.11949565 | F22: =F13/F6 -> 0.14175126 | G22: =G13/G6 -> 0.16206952
A24: 说明：折旧按 2019-2031 年资本开支的 8 年滚动平均计算（与报告口径一致）；股本按上年 FCF 的 60% 回购、25 倍 EPS 估值折算。由于回购采用上年 FCF，EPS 与报告存在 1%-2% 的差异。
A27: 资本开支年度（折旧计算用） | B27: 十亿美元
A28: 2019 | B28: 80
A29: 2020 | B29: 95
A30: 2021 | B30: 130
A31: 2022 | B31: 160
A32: 2023 | B32: 150
A33: 2024 | B33: 230
A34: 2025 | B34: 380
A35: 2026 | B35: 715
A36: 2027 | B36: =C14 -> 900
A37: 2028 | B37: =D14 -> 1020
A38: 2029 | B38: =E14 -> 1100
A39: 2030 | B39: =F14 -> 1120
A40: 2031 | B40: =G14 -> 1100

Sheet 情景对比
A1: 三情景对比（模型输出）
A2: 来自 Python 完整模型：vintage 折旧、FCF 当年回购、8 家公司逐家加总。
A4: 指标 | B4: 2026A | C4: 2031 不裁员 | D4: 2031 每年裁 10% | E4: 2031 每年裁 20% | F4: 10% 相对不裁 | G4: 20% 相对不裁
A5: 收入 | B5: 2936.8 | C5: 4431.987 | D5: 4330.8575 | E5: 4231.5823 | F5: =D5/C5-1 -> -0.022818105 | G5: =E5/C5-1 -> -0.045217803
A6: 经营利润 EBIT | B6: 931 | C6: 1252.2408 | D6: 1344.2369 | E6: 1372.286 | F6: =D6/C6-1 -> 0.073465126 | G6: =E6/C6-1 -> 0.095864277
A7: EBIT 利润率 | B7: 0.31701171 | C7: 0.28254614 | D7: 0.31038585 | E7: 0.32429618 | F7: =D7-C7 -> 0.027839705 | G7: =E7-C7 -> 0.041750043
A8: 净利润 | B8: 763.42 | C8: 1026.8375 | D8: 1102.2742 | E8: 1125.2745 | F8: =D8/C8-1 -> 0.073465126 | G8: =E8/C8-1 -> 0.095864277
A9: EPS（美元） | B9: 9.565468 | C9: 13.540421 | D9: 14.577407 | E9: 14.902997 | F9: =D9/C9-1 -> 0.076584515 | G9: =E9/C9-1 -> 0.10063031
A10: 自由现金流 | B10: 311.84 | C10: 734.49481 | D10: 807.90507 | E10: 828.90899 | F10: =D10/C10-1 -> 0.099946606 | G10: =E10/C10-1 -> 0.12854302
A11: 员工数（千人） | B11: 1189 | C11: 1189 | D11: 702.09261 | E11: 416.15 | F11: =D11/C11-1 -> -0.40951 | G11: =E11/C11-1 -> -0.65
A12: 资本开支 | B12: 715 | C12: 1100 | D12: 1100 | E12: 1100 | F12: =D12/C12-1 -> 0 | G12: =E12/C12-1 -> 0
A13: 折旧 | B13: 190 | C13: 701.875 | D13: 701.875 | E13: 701.875 | F13: =D13/C13-1 -> 0 | G13: =E13/C13-1 -> 0
A14: 折旧/收入 | B14: 0.064696268 | C14: 0.15836576 | D14: 0.16206375 | E14: 0.16586585 | F14: =D14-C14 -> 0.0036979876 | G14: =E14-C14 -> 0.0075000894
A16: 注：EPS 为八家公司合计净利润/合计股本，指数化处理；比例为相对“不裁员”基准的差额。
A18: 逐年路径
A19: EPS（美元） | B19: 2026 | C19: 2027 | D19: 2028 | E19: 2029 | F19: 2030 | G19: 2031
A20: 不裁员 | B20: 9.565468 | C20: 10.920064 | D20: 11.924287 | E20: 12.571372 | F20: 13.101102 | G20: 13.540421
A21: 每年裁 10% | B21: 9.565468 | C21: 11.146643 | D21: 12.365072 | E21: 13.217065 | F21: 13.94445 | G21: 14.577407
A22: 每年裁 20% | B22: 9.565468 | C22: 11.373495 | D22: 12.738258 | E22: 13.666341 | F22: 14.407249 | G22: 14.902997
A24: FCF（十亿美元） | B24: 2026 | C24: 2027 | D24: 2028 | E24: 2029 | F24: 2030 | G24: 2031
A25: 不裁员 | B25: 312 | C25: 283 | D25: 346 | E25: 431 | F25: 569 | G25: 734
A26: 每年裁 10% | B26: 312 | C26: 300 | D26: 379 | E26: 479 | F26: 630 | G26: 808
A27: 每年裁 20% | B27: 312 | C27: 318 | D27: 407 | E27: 512 | F27: 662 | G27: 829

Sheet 敏感性
A1: 敏感性：2026-2031 年 EPS 复合增速
A2: 行：每年裁员速度；列：收入增速相对基准的偏移。
A4: 裁员速度 \ 收入偏移 | B4: -4pt | C4: -2pt | D4: 基准 | E4: +2pt | F4: +4pt
A5: 0 | B5: -0.0337 | C5: 0.022 | D5: 0.072 | E5: 0.1179 | F5: 0.1608
A6: 0.05 | B6: -0.0185 | C6: 0.0339 | D6: 0.0814 | E6: 0.1256 | F6: 0.1671
A7: 0.1 | B7: -0.0079 | C7: 0.0421 | D7: 0.0879 | E7: 0.1307 | F7: 0.1712
A8: 0.15 | B8: -0.001 | C8: 0.0474 | D8: 0.092 | E8: 0.1338 | F8: 0.1735
A9: 0.2 | B9: 0.0013 | C9: 0.0488 | D9: 0.0927 | E9: 0.1341 | F9: 0.1733
A10: 0.25 | B10: -0.0048 | C10: 0.0432 | D10: 0.0876 | E10: 0.1292 | F10: 0.1687

Sheet QQQ
A1: QQQ 情景与概率加权
A2: 指数 EPS 增速 = 65% × 八家公司 + 35% × 其余成分股；年化回报含 0.6% 股息率。
A4: 情景 | B4: 假设 | C4: 指数 EPS 增速 | D4: 期末 PE | E4: 2031 点位 | F4: 年化回报 | G4: 概率 | H4: 加权回报
A5: 牛市：AI 收入兑现 | B5: 收入 +16% 起步，裁员 10%，云维持 40%+ | C5: 0.1393 | D5: 26 | E5: 59196 | F5: 0.1543 | G5: 0.25 | H5: =F5*G5 -> 0.038575
A6: 基准：增长放缓、估值回归 | B6: 收入 +12% 起步，裁员 10%，云降到 25% | C6: 0.0816 | D6: 23 | E6: 40388 | F6: 0.0698 | G6: 0.5 | H6: =F6*G6 -> 0.0349
A7: 熊市：资本开支反噬 | B7: 收入 +7% 起步，裁员 10%，折旧超预期 | C7: -0.0207 | D7: 18 | E7: 19224 | F7: -0.077 | G7: 0.2 | H7: =F7*G7 -> -0.0154
A8: 深度衰退：20% 裁员+需求破坏 | B8: 收入零增长，裁员 20%，估值 14x | C8: -0.0235 | D8: 14 | E8: 14742 | F8: -0.1244 | G8: 0.05 | H8: =F8*G8 -> -0.00622
A9: 概率加权 | E9: =SUMPRODUCT(E5:E8,G5:G8) -> 39574.9 | F9: =SUMPRODUCT(F5:F8,G5:G8) -> 0.051855 | G9: =SUM(G5:G8) -> 1
A12: 指数点位路径
A13: 情景 | B13: 2026 | C13: 2027 | D13: 2028 | E13: 2029 | F13: 2030 | G13: 2031
A14: 牛市：AI 收入兑现 | B14: 29651 | C14: 34458 | D14: 40028 | E14: 45605 | F14: 51958 | G14: 59196
A15: 基准：增长放缓、估值回归 | B15: 29651 | C15: 30789 | D15: 31916 | E15: 34521 | F15: 37340 | G15: 40388
A16: 熊市：资本开支反噬 | B16: 29651 | C16: 24971 | D16: 20472 | E16: 20047 | F16: 19632 | G16: 19224
A17: 深度衰退：20% 裁员+需求破坏 | B17: 29651 | C17: 22584 | D17: 15833 | E17: 15460 | F17: 15097 | G17: 14742

Sheet 季度跟踪
A1: 过去四个季度：裁员、财报与 QQQ
A2: 公告口径，单位：千人；QQQ 为纳斯达克100 季度回报。Q4* 为 9/30-10/28 估计。
A4: 季度 | B4: 公告裁员（千人） | C4: QQQ 当季回报 | D4: 代表性事件 | E4: 宏观/财报主线
A5: 2025Q4 | B5: 17 | C5: 0.0245 | D5: 亚马逊 1.4 万、IBM 约 3,000 | E5: AI 资本开支扩张，财报稳健
A6: 2026Q1 | B6: 38.6 | C6: -0.0593 | D6: 亚马逊 1.6 万、戴尔 1.1 万、Block 4,000、Atlassian 1,600 | E6: 伊朗战争，油价 +79%
A7: 2026Q2 | B7: 32 | C7: 0.2773 | D7: Meta 8,000、思科 4,000、PayPal 4,760、Intuit 3,000 | E7: AI 财报大超预期
A8: 2026Q3 | B8: 5.8 | C8: -0.0376 | D8: 微软 4,800、谷歌滚动优化 | E8: 资本开支焦虑，Meta FCF -91%
A9: 2026Q4* | B9: 61 | C9: -0.04 | D9: 微软 6 万窗口、eBay 9% | E9: 12 月加息概率 78.4%
A11: 事件窗口：五个“纯裁员”公告的股价反应
A12: 公司 | B12: 公告日 | C12: 裁员规模 | D12: 占员工 | E12: 股价反应 | F12: 关键变量
A13: Block | B13: 2026-02-26 | C13: 4000 | D13: 约 50% | E13: +24%（盘后） | F13: 裁员近半 + 费用节省 + AI 叙事
A14: 思科 | B14: 2026-05-14 | C14: 4000 | D14: <5% | E14: +13.4%（当日） | F14: 财报超预期 + 上调指引
A15: Snap | B15: 2026-04-16 | C15: 1000 | D15: 16% | E15: +8%（当日） | F15: AI 生成 65% 新代码
A16: Atlassian | B16: 2026-03-11 | C16: 1600 | D16: 10% | E16: +2%（当日） | F16: 转向 AI/企业销售
A17: PayPal | B17: 2026-05-05 | C17: 4760 | D17: 20%（2-3 年） | E17: -8%（当日） | F17: 裁员 + 下调季度指引
